{
  "routes": {
    "work_assistant": {
      "name": "工作助手",
      "keywords": [
        "工作", "任务", "项目", "计划", "安排", "会议", "报告", "分析",
        "管理", "团队", "协作", "效率", "流程", "优化", "策略", "决策",
        "目标", "执行", "监控", "评估", "改进", "创新", "解决方案",
        "业务", "客户", "市场", "竞争", "预算", "资源", "时间管理",
        "沟通", "协调", "领导", "培训", "技能", "专业", "职场", "晋升"
      ],
      "weight": 1.0,
      "priority": 1
    },
    "chat": {
      "name": "日常对话",
      "keywords": [
        "聊天", "问答", "咨询", "帮助", "建议", "意见", "想法", "感受",
        "生活", "娱乐", "兴趣", "爱好", "朋友", "家庭", "健康", "心情",
        "天气", "新闻", "电影", "音乐", "旅游", "美食", "购物", "运动",
        "学习", "阅读", "思考", "讨论", "分享", "交流", "倾诉", "安慰"
      ],
      "weight": 0.8,
      "priority": 2
    },
    "complex_reasoning": {
      "name": "复杂推理",
      "keywords": [
        "分析", "比较", "评估", "决策", "选择", "判断", "推理", "逻辑",
        "计划", "策略", "方案", "建议", "推荐", "优化", "改善", "解决",
        "如何", "为什么", "什么时候", "哪种", "哪个更好", "怎么样",
        "优缺点", "利弊", "风险", "机会", "挑战", "问题", "困难", "障碍",
        "原因", "结果", "影响", "后果", "效果", "作用", "意义", "价值",
        "深入", "详细", "全面", "系统", "综合", "多角度", "多层次"
      ],
      "weight": 1.2,
      "priority": 1
    }
  },
  "patterns": {
    "question_words": ["如何", "为什么", "什么", "哪个", "哪种", "怎么", "怎样"],
    "comparison_words": ["比较", "对比", "区别", "差异", "异同", "优劣", "好坏"],
    "analysis_words": ["分析", "评估", "判断", "研究", "探讨", "讨论", "思考"],
    "decision_words": ["决策", "选择", "决定", "确定", "考虑", "权衡", "取舍"]
  },
  "settings": {
    "confidence_threshold": 0.6,
    "max_keyword_matches": 10,
    "case_sensitive": false,
    "enable_fuzzy_match": true,
    "cache_ttl": 300000,
    "cache_size": 1000
  }
}